screenshotct/README.MD
screenshotct/__init__.py
screenshotct/requirements.txt
screenshotct/thirdparty.json
screenshotct-0.11.dist-info/LICENSE.rst
screenshotct-0.11.dist-info/METADATA
screenshotct-0.11.dist-info/WHEEL
screenshotct-0.11.dist-info/top_level.txt
screenshotct-0.11.dist-info/RECORD
