Metadata-Version: 2.1
Name: screenshotct
Version: 0.11
Summary: Screenshots - ctypes
Home-page: https://github.com/hansalemaos/screenshotct
Author: Johannes Fischer
Author-email: aulasparticularesdealemaosp@gmail.com
License: MIT
Keywords: screenshots
Classifier: Development Status :: 4 - Beta
Classifier: Programming Language :: Python :: 3 :: Only
Classifier: Programming Language :: Python :: 3.10
Classifier: Topic :: Software Development :: Libraries :: Python Modules
Classifier: Topic :: Utilities
License-File: LICENSE.rst
Requires-Dist: getmonitorresolution
Requires-Dist: numpy
